Emotify/__init__.py
Emotify/emotify_text.py
emotify-0.0.dist-info/licenses/LICENSE.txt
emotify-0.0.dist-info/METADATA
emotify-0.0.dist-info/WHEEL
emotify-0.0.dist-info/top_level.txt
emotify-0.0.dist-info/RECORD
