Metadata-Version: 2.4
Name: Emotify
Version: 0.0
Author: Saurabh Pandey
License: MIT
License-File: LICENSE.txt
Requires-Dist: re
Dynamic: author
Dynamic: description
Dynamic: description-content-type
Dynamic: license
Dynamic: license-file
Dynamic: requires-dist
